LICENSE.txt
README.md
setup.py
minecraft_monitoring_api.egg-info/PKG-INFO
minecraft_monitoring_api.egg-info/SOURCES.txt
minecraft_monitoring_api.egg-info/dependency_links.txt
minecraft_monitoring_api.egg-info/requires.txt
minecraft_monitoring_api.egg-info/top_level.txt
minecraftmonitoring/__init__.py
minecraftmonitoring/markdown.py
minecraftmonitoring/models.py
minecraftmonitoring/monitoring.py
minecraftmonitoring/params.py
minecraftmonitoring/version.py