Metadata-Version: 2.1
Name: minecraft-monitoring-api
Version: 0.1.2
Summary: This is a reverse engineered API wrapper for https://monitoringminecraft.ru/, which allow you automate the process.
Home-page: https://github.com/Xpos587/minecraft-monitoring-api
Author: Xpos587
License: MIT
Classifier: Programming Language :: Python :: 3
Classifier: License :: OSI Approved :: MIT License
Classifier: Operating System :: OS Independent
Requires-Python: >=3.7
License-File: LICENSE.txt
